{
  "$schema": "https://developer.microsoft.com/json-schemas/spfx-build/package-solution.schema.json",
  "solution": {
    "name": "file-client-side-solution",
    "id": "f34bcc80-a594-4e4a-b796-4be643a958ce",
    "version": "1.0.0.0",
    "includeClientSideAssets": true,
    "skipFeatureDeployment": true,
    "isDomainIsolated": false,
    "developer": {
      "name": "",
      "websiteUrl": "",
      "privacyUrl": "",
      "termsOfUseUrl": "",
      "mpnId": "Undefined-1.18.2"
    },
    "metadata": {
      "shortDescription": {
        "default": "file description"
      },
      "longDescription": {
        "default": "file description"
      },
      "screenshotPaths": [],
      "videoUrl": "",
      "categories": []
    },
    "features": [
      {
        "title": "file Feature",
        "description": "The feature that activates elements of the file solution.",
        "id": "e337d159-64be-4dd1-b0e2-fd04cc193e52",
        "version": "1.0.0.0"
      }
    ]
  },
  "paths": {
    "zippedPackage": "solution/file.sppkg"
  }
}
